xgee/__init__.py
xgee/__main__.py
xgee/_version.py
xgee/xgee.py
xgee/core/.git
xgee/core/.gitignore
xgee/core/.gitmodules
xgee/core/.prettierignore
xgee/core/.prettierrc
xgee/core/LICENSE
xgee/core/README.md
xgee/core/package-lock.json
xgee/core/package.json
xgee/core/dep/bluebird/bluebird.js
xgee/core/dep/bluebird/bluebird.min.js
xgee/core/dep/font-awesome/LICENSE.txt
xgee/core/dep/font-awesome/css/all.css
xgee/core/dep/font-awesome/css/all.min.css
xgee/core/dep/font-awesome/css/brands.css
xgee/core/dep/font-awesome/css/brands.min.css
xgee/core/dep/font-awesome/css/fontawesome.css
xgee/core/dep/font-awesome/css/fontawesome.min.css
xgee/core/dep/font-awesome/css/regular.css
xgee/core/dep/font-awesome/css/regular.min.css
xgee/core/dep/font-awesome/css/solid.css
xgee/core/dep/font-awesome/css/solid.min.css
xgee/core/dep/font-awesome/css/svg-with-js.css
xgee/core/dep/font-awesome/css/svg-with-js.min.css
xgee/core/dep/font-awesome/css/v4-shims.css
xgee/core/dep/font-awesome/css/v4-shims.min.css
xgee/core/dep/font-awesome/js/all.js
xgee/core/dep/font-awesome/js/all.min.js
xgee/core/dep/font-awesome/js/brands.js
xgee/core/dep/font-awesome/js/brands.min.js
xgee/core/dep/font-awesome/js/conflict-detection.js
xgee/core/dep/font-awesome/js/conflict-detection.min.js
xgee/core/dep/font-awesome/js/fontawesome.js
xgee/core/dep/font-awesome/js/fontawesome.min.js
xgee/core/dep/font-awesome/js/regular.js
xgee/core/dep/font-awesome/js/regular.min.js
xgee/core/dep/font-awesome/js/solid.js
xgee/core/dep/font-awesome/js/solid.min.js
xgee/core/dep/font-awesome/js/v4-shims.js
xgee/core/dep/font-awesome/js/v4-shims.min.js
xgee/core/dep/font-awesome/webfonts/fa-brands-400.eot
xgee/core/dep/font-awesome/webfonts/fa-brands-400.svg
xgee/core/dep/font-awesome/webfonts/fa-brands-400.ttf
xgee/core/dep/font-awesome/webfonts/fa-brands-400.woff
xgee/core/dep/font-awesome/webfonts/fa-brands-400.woff2
xgee/core/dep/font-awesome/webfonts/fa-regular-400.eot
xgee-0.3.26.dist-info/licenses/LICENSE
xgee-0.3.26.dist-info/METADATA
xgee-0.3.26.dist-info/WHEEL
xgee-0.3.26.dist-info/entry_points.txt
xgee-0.3.26.dist-info/top_level.txt
xgee-0.3.26.dist-info/RECORD
