Metadata-Version: 2.4
Name: XGEE
Version: 0.3.26
Summary: eXtensible Graphical EMOF Editor - a framework for graphical editing single page web-applications
Author-email: Matthias Brunner <matthias.brunner@ils.uni-stuttgart.de>, Andreas Waldvogel <andreas.waldvogel@ils.uni-stuttgart.de>
License: MIT License
Project-URL: Homepage, https://xgee.de
Project-URL: Documentation, https://docs.xgee.de/
Project-URL: Repository, https://gitlab.com/xgee/xgee-core
Keywords: EMOF,editor,web-application,modeling,graphical
Classifier: Programming Language :: Python :: 3
Classifier: License :: OSI Approved :: MIT License
Classifier: Operating System :: OS Independent
Classifier: Environment :: Web Environment
Classifier: Intended Audience :: Developers
Requires-Python: >=3.9
License-File: LICENSE
Requires-Dist: tornado
Requires-Dist: pyyaml
Requires-Dist: eoq1
Requires-Dist: eoq2
Requires-Dist: pyecore
Requires-Dist: watchdog
Requires-Dist: tabulate
Requires-Dist: setuptools
Dynamic: license-file
